{
    "config": {
        "data_prefix": "data/input/",
        "features": [
            0,
            1,
            2,
            4,
            5,
            6,
            7,
            8,
            9,
            10,
            11,
            12,
            13,
            14,
            16,
            18,
            21,
            22,
            28,
            30,
            31,
            32,
            44,
            45,
            46,
            47,
            57,
            60,
            64,
            75,
            76,
            77,
            78,
            79,
            80,
            81,
            82,
            83,
            84,
            85,
            86,
            91,
            92,
            93,
            109,
            110,
            111,
            112,
            117,
            118,
            119,
            137,
            145,
            146,
            151,
            152,
            153,
            154,
            155,
            156,
            157,
            158,
            159,
            160,
            161,
            162,
            163,
            164,
            165,
            166,
            167,
            168,
            1000,
            1001,
            1002,
            1010,
            1011,
            1012
        ],
        "model": {
            "params": {
                "booster": {
                    "bagging_fraction": 0.7,
                    "bagging_freq": 5,
                    "bagging_seed": 3,
                    "categorical_column": [],
                    "feature_fraction": 0.7,
                    "feature_fraction_seed": 2,
                    "learning_rate": 0.02,
                    "max_bin": 255,
                    "metric": "binary_logloss",
                    "num_leaves": 256,
                    "objective": "binary",
                    "task": "train",
                    "verbose": 1
                },
                "train": {
                    "early_stopping_rounds": 50,
                    "num_boost_round": 1000,
                    "verbose_eval": 10
                }
            },
            "path": "models/2_lightgbm.py",
            "target_positive_ratio": 0.17426506525171756
        }
    },
    "feature_importance": {
        "dep_2grams_common_ratio_stop": 2095,
        "dep_2grams_stop_sum_tfidf_q1": 1631,
        "dep_2grams_stop_sum_tfidf_q2": 1592,
        "dep_2grams_stop_tfidf_cosine": 2136,
        "dep_2grams_sum_tfidf_q1": 1274,
        "dep_2grams_sum_tfidf_q2": 1341,
        "dep_2grams_tfidf_cosine": 2576,
        "dep_depth4_limit_in_q1_words_ratio_glove": 166,
        "dep_depth4_limit_in_q2_words_ratio_glove": 104,
        "dep_depth4_limit_wmd_glove": 2348,
        "dep_depth_limit_in_q1_words_ratio_glove": 28,
        "dep_depth_limit_in_q1_words_ratio_glove.1": 15,
        "dep_depth_limit_in_q2_words_ratio_glove": 45,
        "dep_depth_limit_in_q2_words_ratio_glove.1": 39,
        "dep_depth_limit_wmd_glove": 2603,
        "dep_depth_limit_wmd_glove.1": 2968,
        "f0": 2422,
        "f1": 2529,
        "f10": 1430,
        "f109": 1760,
        "f11": 2312,
        "f110": 484,
        "f111": 2883,
        "f112": 2191,
        "f117.q1_freq": 753,
        "f117.q2_freq": 705,
        "f118": 2954,
        "f119": 2094,
        "f12": 1168,
        "f13": 2126,
        "f137.0": 1619,
        "f137.1": 1168,
        "f137.10": 1373,
        "f137.11": 1151,
        "f137.12": 1055,
        "f137.13": 861,
        "f137.14": 929,
        "f137.15": 1323,
        "f137.16": 1228,
        "f137.17": 1136,
        "f137.18": 1574,
        "f137.19": 1839,
        "f137.2": 1179,
        "f137.3": 836,
        "f137.4": 1103,
        "f137.5": 1449,
        "f137.6": 1300,
        "f137.7": 1239,
        "f137.8": 1527,
        "f137.9": 1868,
        "f14": 873,
        "f145": 236,
        "f146": 987,
        "f151.0": 108,
        "f151.1": 311,
        "f151.10": 50,
        "f151.11": 40,
        "f151.12": 36,
        "f151.13": 50,
        "f151.14": 59,
        "f151.15": 42,
        "f151.16": 34,
        "f151.17": 25,
        "f151.18": 40,
        "f151.19": 31,
        "f151.2": 168,
        "f151.20": 29,
        "f151.21": 35,
        "f151.22": 31,
        "f151.23": 29,
        "f151.24": 44,
        "f151.25": 45,
        "f151.26": 47,
        "f151.27": 30,
        "f151.28": 39,
        "f151.29": 26,
        "f151.3": 238,
        "f151.30": 39,
        "f151.31": 53,
        "f151.4": 162,
        "f151.5": 55,
        "f151.6": 60,
        "f151.7": 111,
        "f151.8": 101,
        "f151.9": 51,
        "f152": 807,
        "f153": 1450,
        "f154": 1833,
        "f155": 1934,
        "f156": 1216,
        "f157": 564,
        "f158": 517,
        "f159": 2605,
        "f16": 1689,
        "f160": 2623,
        "f161": 1660,
        "f162": 1141,
        "f163": 2201,
        "f164": 1604,
        "f165": 2072,
        "f166": 2585,
        "f167": 2385,
        "f168": 1767,
        "f18": 1677,
        "f2": 378,
        "f21": 1552,
        "f22": 1994,
        "f28": 2689,
        "f30": 388,
        "f31": 1786,
        "f32": 2247,
        "f4": 1243,
        "f44": 2738,
        "f45": 2695,
        "f46": 2359,
        "f47": 515,
        "f5": 1341,
        "f57.0": 1931,
        "f57.1": 1636,
        "f57.10": 2080,
        "f57.11": 1681,
        "f57.12": 1930,
        "f57.13": 1574,
        "f57.14": 1713,
        "f57.15": 1907,
        "f57.16": 1367,
        "f57.17": 1833,
        "f57.18": 1830,
        "f57.19": 1484,
        "f57.2": 1971,
        "f57.3": 1589,
        "f57.4": 1723,
        "f57.5": 1888,
        "f57.6": 1432,
        "f57.7": 1714,
        "f57.8": 1871,
        "f57.9": 1520,
        "f6": 1865,
        "f60.0": 379,
        "f60.1": 1382,
        "f60.10": 332,
        "f60.11": 1402,
        "f60.12": 1418,
        "f60.13": 1323,
        "f60.14": 1426,
        "f60.15": 1182,
        "f60.16": 1571,
        "f60.17": 1669,
        "f60.18": 1807,
        "f60.19": 1777,
        "f60.2": 1492,
        "f60.3": 1226,
        "f60.4": 1491,
        "f60.5": 1274,
        "f60.6": 1467,
        "f60.7": 1809,
        "f60.8": 1850,
        "f60.9": 1758,
        "f64.0": 1791,
        "f64.1": 1457,
        "f64.10": 1810,
        "f64.11": 1352,
        "f64.12": 1542,
        "f64.13": 1431,
        "f64.14": 1558,
        "f64.15": 1677,
        "f64.16": 1663,
        "f64.17": 1356,
        "f64.18": 1698,
        "f64.19": 1765,
        "f64.2": 1529,
        "f64.3": 1684,
        "f64.4": 1619,
        "f64.5": 1782,
        "f64.6": 1667,
        "f64.7": 1520,
        "f64.8": 1667,
        "f64.9": 1747,
        "f7": 442,
        "f75": 1198,
        "f76": 1329,
        "f77": 1848,
        "f78": 1786,
        "f79": 1691,
        "f8": 486,
        "f80": 1695,
        "f81": 1715,
        "f82": 1718,
        "f83": 1125,
        "f84": 1234,
        "f85": 841,
        "f86": 1061,
        "f9": 1173,
        "f91": 2745,
        "f92": 2920,
        "f93": 2005
    },
    "results": {
        "accuracy": 0.9381967851263665,
        "auc": 0.9736592195592009,
        "f1_score": 0.8151069206035327,
        "log_loss": 0.14680398272672524,
        "precision": 0.851460527141328,
        "pred_mean": 0.18690004443417585,
        "recall": 0.7817304793488091,
        "train_log_loss": 0.06653524203252797
    }
}